LICENSE
MANIFEST.in
README.rst
setup.py
tox.ini
pire/__init__.py
pire/exceptions.py
pire/local_os.py
pire/regex_engine.py
pire/ui.py
pire.egg-info/PKG-INFO
pire.egg-info/SOURCES.txt
pire.egg-info/dependency_links.txt
pire.egg-info/entry_points.txt
pire.egg-info/requires.txt
pire.egg-info/top_level.txt