Metadata-Version: 1.1
Name: pire
Version: 0.2.0
Summary: Python Interactive Regular Expression
Home-page: https://github.com/johannestaas/pire
Author: Johan Nestaas
Author-email: johannestaas@gmail.com
License: GPLv3
Keywords: python regex re regular expressions
Platform: UNKNOWN
Classifier: Development Status :: 4 - Beta
Classifier: Environment :: Console
Classifier: Environment :: X11 Applications :: Qt
Classifier: Environment :: MacOS X
Classifier: Environment :: Win32 (MS Windows)
Classifier: Operating System :: POSIX
Classifier: Operating System :: MacOS :: MacOS X
Classifier: Operating System :: Microsoft :: Windows
Classifier: Programming Language :: Python
